LICENSE
MANIFEST.in
README.rst
setup.cfg
setup.py
django_import_export_pandas.egg-info/PKG-INFO
django_import_export_pandas.egg-info/SOURCES.txt
django_import_export_pandas.egg-info/dependency_links.txt
django_import_export_pandas.egg-info/not-zip-safe
django_import_export_pandas.egg-info/top_level.txt
import_export_pandas/__init__.py
import_export_pandas/formats.py
import_export_pandas/mixins.py
import_export_pandas/resources.py
import_export_pandas/tests/__init__.py
import_export_pandas/tests/factories.py
import_export_pandas/tests/test_formats.py
import_export_pandas/tests/test_resources.py
import_export_pandas/tests/testapp/__init__.py
import_export_pandas/tests/testapp/admin.py
import_export_pandas/tests/testapp/apps.py
import_export_pandas/tests/testapp/models.py
import_export_pandas/tests/testapp/resources.py
import_export_pandas/tests/testapp/tests.py
import_export_pandas/tests/testapp/views.py
import_export_pandas/tests/testapp/migrations/0001_initial.py
import_export_pandas/tests/testapp/migrations/__init__.py